rtrv_my_chat_server-1.0.6.data/scripts/server_gui
rtrv_my_chat_server-1.0.6.data/scripts/server_run
server/__init__.py
server/decos.py
server/reg_new_user.py
server/server.py
server/server_db.py
server/server_gui.py
server/log/__init__.py
server/log/client_log_config.py
server/log/server_log_config.py
server/service/__init__.py
server/service/serv_descr.py
server/service/service.py
server/service/settings.ini
server/service/setup.py
server/service/test_service.py
rtrv_my_chat_server-1.0.6.dist-info/METADATA
rtrv_my_chat_server-1.0.6.dist-info/WHEEL
rtrv_my_chat_server-1.0.6.dist-info/top_level.txt
rtrv_my_chat_server-1.0.6.dist-info/RECORD
